indoorplants/__init__.py
indoorplants/analysis/__init__.py
indoorplants/analysis/exploratory.py
indoorplants/analysis/features.py
indoorplants/analysis/wrangle.py
indoorplants/validation/__init__.py
indoorplants/validation/boundaries.py
indoorplants/validation/calibration.py
indoorplants/validation/crossvalidate.py
indoorplants/validation/curves.py
indoorplants-1.0.dist-info/LICENSE
indoorplants-1.0.dist-info/METADATA
indoorplants-1.0.dist-info/WHEEL
indoorplants-1.0.dist-info/top_level.txt
indoorplants-1.0.dist-info/RECORD
