Metadata-Version: 2.1
Name: indoorplants
Version: 1.0
Summary: Tools for data analysis and model validation
Home-page: https://github.com/lermana/indoorplants
Author: Abe Lerman
Author-email: UNKNOWN
License: UNKNOWN
Platform: UNKNOWN
Requires-Dist: numpy
Requires-Dist: scipy
Requires-Dist: pandas
Requires-Dist: sklearn
Requires-Dist: matplotlib
Requires-Dist: requests
